{"cameraMode":{"drawMode":0,"name":"Shaded","section":"Shading Mode"},"sceneLighting":true,"audioPlay":false,"sceneViewState":{"showFog":true,"showMaterialUpdate":false,"showSkybox":true,"showFlares":true,"showImageEffects":true,"showParticleSystems":true},"in2DMode":false,"pivot":{"x":-0.08641480654478073,"y":8.626285552978516,"z":-8.480233192443848},"rotation":{"x":0.3044111728668213,"y":-0.00483382074162364,"z":0.0015090106753632427,"w":0.9525803923606873},"size":1.8898181915283204,"orthographic":false}